splicemachinesa/__init__.py
splicemachinesa/base.py
splicemachinesa/constants.py
splicemachinesa/pyodbc.py
splicemachinesa/reflection.py
splicemachinesa/requirements.py
splicemachinesa/splice_machine.py
splicemachinesa/utilities.py
splicemachinesa-0.3.6.dist-info/LICENSE.txt
splicemachinesa-0.3.6.dist-info/METADATA
splicemachinesa-0.3.6.dist-info/WHEEL
splicemachinesa-0.3.6.dist-info/entry_points.txt
splicemachinesa-0.3.6.dist-info/top_level.txt
splicemachinesa-0.3.6.dist-info/RECORD
