Metadata-Version: 2.1
Name: splicemachinesa
Version: 0.3.6
Summary: SQLAlchemy support for Splice Machine RDBMS
Home-page: https://splicemachine.com
Author: Amrit Baveja
Author-email: abaveja@splicemachine.com
License: Apache License 2.0
Download-URL: https://splice-releases.s3.amazonaws.com/splice-sqlalchemy/splicemachinesa-0.3.6.dev0.tar.gz
Keywords: sqlalchemy,splice,machine,splice machine,odbc,driver,sqlalchemy driver
Platform: All
Classifier: Development Status :: 3 - Alpha
Classifier: Intended Audience :: Developers
Classifier: License :: OSI Approved :: Apache Software License
Classifier: Operating System :: MacOS :: MacOS X
Classifier: Operating System :: POSIX :: Linux
Classifier: Topic :: Database
Requires-Dist: sqlalchemy
Requires-Dist: pyodbc (>=4.0.26)
